geometalab.drf_utm_zone_info-0.2.0.dist-info/DESCRIPTION.rst
geometalab.drf_utm_zone_info-0.2.0.dist-info/METADATA
geometalab.drf_utm_zone_info-0.2.0.dist-info/RECORD
geometalab.drf_utm_zone_info-0.2.0.dist-info/WHEEL
geometalab.drf_utm_zone_info-0.2.0.dist-info/metadata.json
geometalab.drf_utm_zone_info-0.2.0.dist-info/top_level.txt
utm_zone_info/__init__.py
utm_zone_info/coordinate_reference_system.py
utm_zone_info/serializers.py
utm_zone_info/urls.py
utm_zone_info/views.py
utm_zone_info/__pycache__/__init__.cpython-35.pyc
utm_zone_info/__pycache__/coordinate_reference_system.cpython-35.pyc
utm_zone_info/__pycache__/serializers.cpython-35.pyc
utm_zone_info/__pycache__/urls.cpython-35.pyc
utm_zone_info/__pycache__/views.cpython-35.pyc
